retryit/__init__.py
retryit/retry.py
pyretryit_rj-1.0.0.dist-info/METADATA
pyretryit_rj-1.0.0.dist-info/WHEEL
pyretryit_rj-1.0.0.dist-info/RECORD
